d3wordcloud.py
d3wordcloud-0.0.1.dist-info/LICENSE
d3wordcloud-0.0.1.dist-info/METADATA
d3wordcloud-0.0.1.dist-info/WHEEL
d3wordcloud-0.0.1.dist-info/top_level.txt
d3wordcloud-0.0.1.dist-info/RECORD
