Metadata-Version: 2.1
Name: d3wordcloud
Version: 0.0.1
Summary: A simple Jupyter (Lab/Notebook) port of Jason Davies d3 JS wordcloud generator https://www.jasondavies.com/wordcloud/
Home-page: https://github.com/do-me/d3wordcloud
Author: Dominik Weckmüller
Author-email: dominik@geo.rocks
License: UNKNOWN
Platform: UNKNOWN
Classifier: Programming Language :: Python :: 3
Classifier: Programming Language :: Python :: 3.7
Classifier: Programming Language :: Python :: 3.8
Classifier: Topic :: Software Development :: Libraries :: Python Modules
Classifier: License :: OSI Approved :: MIT License
Classifier: Operating System :: OS Independent
Requires-Python: >=3
Provides-Extra: dev
Requires-Dist: ipython ; extra == 'dev'
Requires-Dist: check-manifest ; extra == 'dev'
Requires-Dist: twine ; extra == 'dev'
